LICENSE.txt
MANIFEST.in
README.md
setup.cfg
setup.py
tw2/__init__.py
tw2.wysihtml5.egg-info/PKG-INFO
tw2.wysihtml5.egg-info/SOURCES.txt
tw2.wysihtml5.egg-info/dependency_links.txt
tw2.wysihtml5.egg-info/entry_points.txt
tw2.wysihtml5.egg-info/namespace_packages.txt
tw2.wysihtml5.egg-info/not-zip-safe
tw2.wysihtml5.egg-info/requires.txt
tw2.wysihtml5.egg-info/top_level.txt
tw2/bootstrap/__init__.py
tw2/bootstrap/wysihtml5/__init__.py
tw2/bootstrap/wysihtml5/samples.py
tw2/bootstrap/wysihtml5/widgets.py
tw2/bootstrap/wysihtml5/static/bootstrap-wysihtml5-0.0.2.css
tw2/bootstrap/wysihtml5/static/bootstrap-wysihtml5-0.0.2.js
tw2/bootstrap/wysihtml5/static/bootstrap-wysihtml5-0.0.2.min.js
tw2/bootstrap/wysihtml5/static/bootstrap-wysihtml5.css
tw2/bootstrap/wysihtml5/static/bootstrap-wysihtml5.js
tw2/bootstrap/wysihtml5/static/bootstrap-wysihtml5.min.js
tw2/wysihtml5/__init__.py
tw2/wysihtml5/samples.py
tw2/wysihtml5/widgets.py
tw2/wysihtml5/static/advanced.js
tw2/wysihtml5/static/editor.css
tw2/wysihtml5/static/simple.js
tw2/wysihtml5/static/wysihtml5-0.3.0.js
tw2/wysihtml5/static/wysihtml5-0.3.0.min.js
tw2/wysihtml5/static/wysihtml5.js
tw2/wysihtml5/static/wysihtml5.min.js
tw2/wysihtml5/templates/__init__.py
tw2/wysihtml5/templates/__init__.pyc
tw2/wysihtml5/templates/wysihtml5.mak