Metadata-Version: 1.1
Name: tw2.wysihtml5
Version: 0.3
Summary: WYSIHTML5 widget for ToscaWidgets2
Home-page: https://github.com/toscawidgets/tw2.wysihtml5
Author: Moritz Schlarb
Author-email: moschlar@metalabs.de
License: BSD 2-clause
Keywords: toscawidgets.widgets
Platform: UNKNOWN
Classifier: Development Status :: 4 - Beta
Classifier: Environment :: Web Environment
Classifier: Environment :: Web Environment :: ToscaWidgets
Classifier: Topic :: Software Development :: Libraries :: Python Modules
Classifier: Topic :: Software Development :: Widget Sets
Classifier: Intended Audience :: Developers
Classifier: Operating System :: OS Independent
Classifier: Programming Language :: Python
Classifier: License :: OSI Approved :: BSD License
